__init__.py
py_request_nacos/__init__.py
py_request_nacos/example.py
py2nacos-0.1.0.dist-info/LICENSE
py2nacos-0.1.0.dist-info/METADATA
py2nacos-0.1.0.dist-info/WHEEL
py2nacos-0.1.0.dist-info/top_level.txt
py2nacos-0.1.0.dist-info/RECORD
