Metadata-Version: 2.1
Name: py2nacos
Version: 0.1.0
Summary: A tool that allows an app registers itself with Nacos
Author-email: lidaning <453882101@qq.com>
Project-URL: Homepage, https://github.com/relidaning/py2nacos
Project-URL: Bug Tracker, https://github.com/relidaning/py2nacos/issues
Classifier: Programming Language :: Python :: 3
Classifier: Operating System :: OS Independent
Requires-Python: >=3.7
License-File: LICENSE
